ctkchart/CTkLine.py
ctkchart/CTkLineChart.py
ctkchart/FontStyle.py
ctkchart/ThemeManager.py
ctkchart/Utils.py
ctkchart/Validate.py
ctkchart/__init__.py
ctkchart-2.1.9.dist-info/licenses/LICENSE
ctkchart-2.1.9.dist-info/METADATA
ctkchart-2.1.9.dist-info/WHEEL
ctkchart-2.1.9.dist-info/top_level.txt
ctkchart-2.1.9.dist-info/RECORD
