Metadata-Version: 2.4
Name: ctkchart
Version: 2.1.9
Summary: ctkchart is a Python library for creating live updating line charts in customtkinter.
Author: Thisal-D
License: Copyright (c) 2024 The Python Packaging Authority
Project-URL: homepage, https://github.com/Thisal-D/ctkchart
Project-URL: repository, https://github.com/Thisal-D/ctkchart
Project-URL: issues, https://github.com/Thisal-D/ctkchart/issues
Requires-Python: >=3.0
License-File: LICENSE
Requires-Dist: customtkinter
Provides-Extra: dev
Dynamic: license-file
